ojtest/__init__.py
ojtest/rand_list.py
ojtest/rand_str.py
ojtest/rand_tree.py
ojtest-0.0.3.9.dist-info/LICENSE
ojtest-0.0.3.9.dist-info/METADATA
ojtest-0.0.3.9.dist-info/WHEEL
ojtest-0.0.3.9.dist-info/top_level.txt
ojtest-0.0.3.9.dist-info/RECORD
