Metadata-Version: 2.1
Name: ojtest
Version: 0.0.3.9
Summary: A testcase generator for online judges.
Author-email: Vela <velayf@outlook.com>
Project-URL: Homepage, https://github.com/VelaQ/oj_testcase
Project-URL: Bug Tracker, https://github.com/VelaQ/oj_testcase/issues
Classifier: Programming Language :: Python :: 3
Classifier: License :: OSI Approved :: MIT License
Classifier: Operating System :: OS Independent
Requires-Python: >=3.0
License-File: LICENSE
